textstat_id/__init__.py
textstat_id/analyzer.py
textstat_id/convert_word_to_number.py
textstat_id/counter.py
textstat_id/duplication_checker.py
textstat_id/hashtag_extract.py
textstat_id/readability.py
textstat_id/sentiment.py
textstat_id/url_exctract.py
textstat_id/utils.py
textstat_id/data/kata_baku.json
textstat_id/data/kata_negatif.json
textstat_id/data/kata_penguat_negatif.json
textstat_id/data/kata_penguat_positif.json
textstat_id/data/kata_positif.json
textstat_id-0.0.7.dist-info/METADATA
textstat_id-0.0.7.dist-info/WHEEL
textstat_id-0.0.7.dist-info/top_level.txt
textstat_id-0.0.7.dist-info/RECORD
