Metadata-Version: 2.4
Name: textstat_id
Version: 0.0.7
Summary: Library untuk analisis statistik teks Bahasa Indonesia
Author-email: rifqanzalbina <zalbinarifqan19@gmail.com>
License: MIT
Project-URL: Homepage, https://github.com/rifqanzalbina/textstat_id
Project-URL: Bug Tracker, https://github.com/rifqanzalbina/textstat_id/issues
Classifier: Programming Language :: Python :: 3
Classifier: License :: OSI Approved :: MIT License
Classifier: Operating System :: OS Independent
Classifier: Natural Language :: Indonesian
Classifier: Topic :: Text Processing :: Linguistic
Requires-Python: >=3.6
Requires-Dist: nltk>=3.6.0
Requires-Dist: pandas>=1.0.0
